dfktools/__init__.py
dfktools/airdrop_example.py
dfktools/alchemist_example.py
dfktools/assisting_example.py
dfktools/auction_example.py
dfktools/bridge_example.py
dfktools/consumable_example.py
dfktools/dex_example.py
dfktools/duel_example.py
dfktools/erc20_example.py
dfktools/genes_encode_example.py
dfktools/genes_example.py
dfktools/hero_example.py
dfktools/land_example.py
dfktools/meditation_example.py
dfktools/pet_example.py
dfktools/profile_example.py
dfktools/quest_example.py
dfktools/raffle_example.py
dfktools/stone_carver_example.py
dfktools/summoning_example.py
dfktools/wishing_well_quest_example.py
dfktools/airdrop/__init__.py
dfktools/airdrop/airdrop.py
dfktools/alchemist/__init__.py
dfktools/alchemist/alchemist.py
dfktools/auctions/__init__.py
dfktools/auctions/auction.py
dfktools/auctions/auction_core.py
dfktools/auctions/land.py
dfktools/auctions/pet.py
dfktools/auctions/hero/__init__.py
dfktools/auctions/hero/rent_auctions.py
dfktools/auctions/hero/sale_auctions.py
dfktools/auctions/utils/__init__.py
dfktools/auctions/utils/utils.py
dfktools/bridge/__init__.py
dfktools/bridge/dfktears_bridge.py
dfktools/bridge/hero_bridge.py
dfktools/consumable/__init__.py
dfktools/consumable/consumable.py
dfktools/dex/__init__.py
dfktools/dex/crystal.py
dfktools/dex/erc1155.py
dfktools/dex/erc20.py
dfktools/dex/item_erc1155.py
dfktools/dex/jade.py
dfktools/dex/jewel.py
dfktools/dex/master_gardener.py
dfktools/dex/uniswap_v2_factory.py
dfktools/dex/uniswap_v2_pair.py
dfktools/dex/uniswap_v2_router.py
dfktools/dex/utils/__init__.py
dfktools/dex/utils/utils.py
dfktools/duel/__init__.py
dfktools/duel/duel.py
dfktools/duel/utils/__init__.py
dfktools/duel/utils/utils.py
dfktools/genes/__init__.py
dfktools/genes/gene_science_v1.py
dfktools/genes/gene_science_v2.py
dfktools/hero/__init__.py
dfktools/hero/hero_core.py
dfktools/hero/heroes.py
dfktools/hero/utils/__init__.py
dfktools/hero/utils/utils.py
dfktools/land/__init__.py
dfktools/land/land.py
dfktools-0.3.2.dist-info/LICENSE
dfktools-0.3.2.dist-info/METADATA
dfktools-0.3.2.dist-info/WHEEL
dfktools-0.3.2.dist-info/top_level.txt
dfktools-0.3.2.dist-info/RECORD
