Metadata-Version: 2.1
Name: dfktools
Version: 0.3.2
Summary: A toolbox for DefiKingdoms
Home-page: https://github.com/0rtis/dfktools
Author: Ortis
Author-email: Ortis <ortis@ortis.io>
License: MIT License
Project-URL: Bug Tracker, https://github.com/0rtis/dfktools/issues
Keywords: blockchain,web3,NFT,etherum,game
Classifier: Development Status :: 4 - Beta
Classifier: Environment :: Console
Classifier: Programming Language :: Python :: 3
Requires-Python: >=3.8
License-File: LICENSE
Requires-Dist: requests
Requires-Dist: web3
Requires-Dist: importlib-metadata ; python_version < "3.8"
